stoolpy/__init__.py
stoolpy/solvers.py
stoolpy-0.0.3.dist-info/LICENSE
stoolpy-0.0.3.dist-info/METADATA
stoolpy-0.0.3.dist-info/WHEEL
stoolpy-0.0.3.dist-info/top_level.txt
stoolpy-0.0.3.dist-info/RECORD
