Metadata-Version: 2.1
Name: stoolpy
Version: 0.0.3
Summary: A Scientific Computing Toolbox package
Author: Qcuincy (Quincy Sproul)
Author-email: <quincy.sproul@gmail.com>
Keywords: python,numerical,science,scientific,modelling,data,visualizer
Classifier: Development Status :: 1 - Planning
Classifier: Intended Audience :: Developers
Classifier: Programming Language :: Python :: 3
Classifier: Operating System :: Unix
Classifier: Operating System :: MacOS :: MacOS X
Classifier: Operating System :: Microsoft :: Windows
License-File: LICENSE
Requires-Dist: numpy
Requires-Dist: matplotlib
Requires-Dist: scipy
